{
  "colors": {
    "primary": {
      "50": "#eff6ff",
      "100": "#dbeafe",
      "200": "#bfdbfe",
      "300": "#93c5fd",
      "400": "#60a5fa",
      "500": "#3b82f6",
      "600": "#2563eb",
      "700": "#1d4ed8",
      "800": "#1e40af",
      "900": "#1e3a8a",
      "950": "#172554"
    },
    "neutral": {
      "0": "#ffffff",
      "50": "#f9fafb",
      "100": "#f3f4f6",
      "200": "#e5e7eb",
      "300": "#d1d5db",
      "400": "#9ca3af",
      "500": "#6b7280",
      "600": "#4b5563",
      "700": "#374151",
      "800": "#1f2937",
      "900": "#111827",
      "950": "#030712"
    },
    "success": {
      "500": "#10b981",
      "600": "#059669",
      "700": "#047857"
    },
    "warning": {
      "500": "#f59e0b",
      "600": "#d97706",
      "700": "#b45309"
    },
    "error": {
      "500": "#ef4444",
      "600": "#dc2626",
      "700": "#b91c1c"
    }
  },
  "spacing": {
    "0": "0px",
    "1": "4px",
    "2": "8px",
    "3": "12px",
    "4": "16px",
    "5": "20px",
    "6": "24px",
    "7": "28px",
    "8": "32px",
    "10": "40px",
    "12": "48px",
    "16": "64px",
    "20": "80px",
    "24": "96px",
    "32": "128px"
  },
  "typography": {
    "fontFamily": {
      "sans": ["Inter", "ui-sans-serif", "system-ui"],
      "mono": ["JetBrains Mono", "ui-monospace", "monospace"]
    },
    "fontSize": {
      "xs": ["12px", "16px"],
      "sm": ["14px", "20px"],
      "base": ["16px", "24px"],
      "lg": ["18px", "28px"],
      "xl": ["20px", "28px"],
      "2xl": ["24px", "32px"],
      "3xl": ["30px", "36px"],
      "4xl": ["36px", "40px"],
      "5xl": ["48px", "48px"]
    },
    "fontWeight": {
      "normal": "400",
      "medium": "500",
      "semibold": "600",
      "bold": "700"
    },
    "letterSpacing": {
      "tight": "-0.025em",
      "normal": "0em",
      "wide": "0.025em"
    }
  },
  "borderRadius": {
    "none": "0px",
    "sm": "2px",
    "base": "4px",
    "md": "6px",
    "lg": "8px",
    "xl": "12px",
    "2xl": "16px",
    "full": "9999px"
  },
  "shadows": {
    "sm": "0 1px 2px 0 rgb(0 0 0 / 0.05)",
    "base": "0 1px 3px 0 rgb(0 0 0 / 0.1), 0 1px 2px -1px rgb(0 0 0 / 0.1)",
    "md": "0 4px 6px -1px rgb(0 0 0 / 0.1), 0 2px 4px -2px rgb(0 0 0 / 0.1)",
    "lg": "0 10px 15px -3px rgb(0 0 0 / 0.1), 0 4px 6px -4px rgb(0 0 0 / 0.1)",
    "xl": "0 20px 25px -5px rgb(0 0 0 / 0.1), 0 8px 10px -6px rgb(0 0 0 / 0.1)"
  },
  "transitions": {
    "duration": {
      "fast": "150ms",
      "normal": "200ms",
      "slow": "300ms"
    },
    "easing": {
      "ease": "cubic-bezier(0.4, 0, 0.2, 1)",
      "easeIn": "cubic-bezier(0.4, 0, 1, 1)",
      "easeOut": "cubic-bezier(0, 0, 0.2, 1)"
    }
  }
}